matos_azure_provider/__init__.py
matos_azure_provider/config.py
matos_azure_provider/provider.py
matos_azure_provider/lib/__init__.py
matos_azure_provider/lib/auth.py
matos_azure_provider/lib/base_provider.py
matos_azure_provider/lib/factory.py
matos_azure_provider/lib/loader.py
matos_azure_provider/plugins/__init__.py
matos_azure_provider/plugins/cluster.py
matos_azure_provider/plugins/instance.py
matos_azure_provider/plugins/key_vault.py
matos_azure_provider/plugins/monitor.py
matos_azure_provider/plugins/network.py
matos_azure_provider/plugins/postgresql.py
matos_azure_provider/plugins/sql.py
matos_azure_provider/plugins/storage.py
matos_azure_provider-1.0.10.dist-info/LICENSE
matos_azure_provider-1.0.10.dist-info/METADATA
matos_azure_provider-1.0.10.dist-info/WHEEL
matos_azure_provider-1.0.10.dist-info/top_level.txt
matos_azure_provider-1.0.10.dist-info/RECORD
